setup.py
pmnlp/__init__.py
pmnlp/sentence.py
pmnlp/word.py
pmnlp.egg-info/PKG-INFO
pmnlp.egg-info/SOURCES.txt
pmnlp.egg-info/dependency_links.txt
pmnlp.egg-info/requires.txt
pmnlp.egg-info/top_level.txt